tests/__init__.py
tests/test_topsis.py
topsis/__init__.py
topsis/topsis.py
102203166_topsis-0.1.0.dist-info/METADATA
102203166_topsis-0.1.0.dist-info/WHEEL
102203166_topsis-0.1.0.dist-info/top_level.txt
102203166_topsis-0.1.0.dist-info/RECORD
