Metadata-Version: 2.2
Name: 102203166-topsis
Version: 0.1.0
Summary: A Python package to implement the TOPSIS method for multi-criteria decision analysis.
Home-page: https://github.com/stuti-go/topsis-package
Author: Stuti Goyal
Author-email: gstu180@gmail.com
Classifier: Programming Language :: Python :: 3
Classifier: Operating System :: OS Independent
Requires-Python: >=3.6
Requires-Dist: numpy
Dynamic: author
Dynamic: author-email
Dynamic: classifier
Dynamic: description-content-type
Dynamic: home-page
Dynamic: requires-dist
Dynamic: requires-python
Dynamic: summary
